cache_manager.py
error_helpers.py
mock_data.py
sap_datasphere_mcp_server.py
telemetry.py
tool_descriptions.py
auth/__init__.py
auth/authorization.py
auth/consent_manager.py
auth/data_filter.py
auth/datasphere_auth_connector.py
auth/input_validator.py
auth/oauth_handler.py
auth/sql_sanitizer.py
auth/tool_validators.py
iflow_mcp_mariodefelipe_sap_datasphere_mcp-1.0.13.dist-info/licenses/LICENSE
iflow_mcp_mariodefelipe_sap_datasphere_mcp-1.0.13.dist-info/licenses/NOTICE
iflow_mcp_mariodefelipe_sap_datasphere_mcp-1.0.13.dist-info/METADATA
iflow_mcp_mariodefelipe_sap_datasphere_mcp-1.0.13.dist-info/WHEEL
iflow_mcp_mariodefelipe_sap_datasphere_mcp-1.0.13.dist-info/entry_points.txt
iflow_mcp_mariodefelipe_sap_datasphere_mcp-1.0.13.dist-info/top_level.txt
iflow_mcp_mariodefelipe_sap_datasphere_mcp-1.0.13.dist-info/RECORD
