Metadata-Version: 2.4
Name: iflow-mcp_mariodefelipe_sap-datasphere-mcp
Version: 1.0.13
Summary: Model Context Protocol server for SAP Datasphere integration with 45 tools including Smart Query with enhanced aggregation support for simple and GROUP BY queries
Home-page: https://github.com/MarioDeFelipe/sap-datasphere-mcp
Author: Mario DeFelipe
Author-email: Mario DeFelipe <mario.defelipe@example.com>
Maintainer-email: Mario DeFelipe <mario.defelipe@example.com>
License: MIT
Project-URL: Homepage, https://github.com/MarioDeFelipe/sap-datasphere-mcp
Project-URL: Documentation, https://github.com/MarioDeFelipe/sap-datasphere-mcp#readme
Project-URL: Repository, https://github.com/MarioDeFelipe/sap-datasphere-mcp
Project-URL: Issues, https://github.com/MarioDeFelipe/sap-datasphere-mcp/issues
Project-URL: Changelog, https://github.com/MarioDeFelipe/sap-datasphere-mcp/releases
Keywords: sap,datasphere,mcp,model-context-protocol,data-warehouse,etl,odata,oauth,analytics,cloud
Classifier: Development Status :: 5 - Production/Stable
Classifier: Intended Audience :: Developers
Classifier: Intended Audience :: Information Technology
Classifier: Intended Audience :: System Administrators
Classifier: Topic :: Database
Classifier: Topic :: Database :: Database Engines/Servers
Classifier: Topic :: Software Development :: Libraries :: Python Modules
Classifier: Topic :: System :: Distributed Computing
Classifier: License :: OSI Approved :: MIT License
Classifier: Operating System :: OS Independent
Classifier: Programming Language :: Python :: 3
Classifier: Programming Language :: Python :: 3.10
Classifier: Programming Language :: Python :: 3.11
Classifier: Programming Language :: Python :: 3.12
Classifier: Programming Language :: Python :: 3 :: Only
Classifier: Framework :: AsyncIO
Classifier: Natural Language :: English
Requires-Python: >=3.10
License-File: LICENSE
License-File: NOTICE
Requires-Dist: mcp>=0.1.0
Requires-Dist: aiohttp>=3.9.1
Requires-Dist: cryptography>=41.0.7
Requires-Dist: python-dotenv>=1.0.0
Provides-Extra: dev
Requires-Dist: pytest>=7.4.0; extra == "dev"
Requires-Dist: pytest-asyncio>=0.21.0; extra == "dev"
Requires-Dist: pytest-cov>=4.1.0; extra == "dev"
Requires-Dist: black>=23.7.0; extra == "dev"
Requires-Dist: ruff>=0.0.285; extra == "dev"
Requires-Dist: mypy>=1.5.0; extra == "dev"
Provides-Extra: docs
Requires-Dist: sphinx>=7.1.0; extra == "docs"
Requires-Dist: sphinx-rtd-theme>=1.3.0; extra == "docs"
Provides-Extra: test
Requires-Dist: pytest>=7.4.0; extra == "test"
Requires-Dist: pytest-asyncio>=0.21.0; extra == "test"
Requires-Dist: pytest-cov>=4.1.0; extra == "test"
Requires-Dist: responses>=0.23.0; extra == "test"
Dynamic: author
Dynamic: home-page
Dynamic: license-file
Dynamic: requires-python
